MANIFEST.in
README.txt
setup.py
Merlot.egg-info/PKG-INFO
Merlot.egg-info/SOURCES.txt
Merlot.egg-info/dependency_links.txt
Merlot.egg-info/entry_points.txt
Merlot.egg-info/not-zip-safe
Merlot.egg-info/requires.txt
Merlot.egg-info/top_level.txt
merlot/__init__.py
merlot/app.py
merlot/auth.py
merlot/client.py
merlot/configure.zcml
merlot/ftesting.zcml
merlot/interfaces.py
merlot/lib.py
merlot/project.py
merlot/reports.py
merlot/resource.py
merlot/tests.py
merlot/vocabularies.py
merlot/app_templates/control_panel.pt
merlot/app_templates/dashboard.pt
merlot/app_templates/flashmessages.pt
merlot/app_templates/footer.pt
merlot/app_templates/form.pt
merlot/app_templates/head.pt
merlot/app_templates/logo.pt
merlot/app_templates/master.pt
merlot/app_templates/navigationbar.pt
merlot/app_templates/pathbar.pt
merlot/app_templates/personalbar.pt
merlot/auth_templates/userfolder_index.pt
merlot/client_templates/client_index.pt
merlot/client_templates/clientcontainer_index.pt
merlot/doctests/catalog.rst
merlot/doctests/functional_auth.rst
merlot/doctests/functional_client.rst
merlot/doctests/functional_reports.rst
merlot/doctests/functional_simpleproject.rst
merlot/doctests/setup.rst
merlot/doctests/starred_tasks.rst
merlot/locales/merlot.pot
merlot/locales/en/LC_MESSAGES/merlot.po
merlot/locales/es/LC_MESSAGES/merlot.po
merlot/locales/ja/LC_MESSAGES/merlot.po
merlot/project_templates/add_log_ajax_form.pt
merlot/project_templates/project_index.pt
merlot/project_templates/projectcontainer_index.pt
merlot/project_templates/projects_listing.pt
merlot/project_templates/task_index.pt
merlot/reports_templates/logsreport_viewlet.pt
merlot/reports_templates/reports_index.pt
merlot/reports_templates/tasksreport_viewlet.pt
merlot/static/README.txt
merlot/static/copyevents.js
merlot/static/jquery.collapse.js
merlot/static/jquery.cookie.js
merlot/static/merlot.js
merlot/static/quicklog.js
merlot/static/style.css
merlot/static/datepicker/index.html
merlot/static/datepicker/css/ui.daterangepicker.css
merlot/static/datepicker/js/daterangepicker.jQuery.js
merlot/static/images/accept.png
merlot/static/images/add.png
merlot/static/images/ajax-load.gif
merlot/static/images/arrows.png
