Metadata-Version: 1.0
Name: Merlot
Version: 0.2
Summary: A web-based project management software
Home-page: http://code.google.com/p/merlot/
Author: Emanuel Sartor, Silvestre Huens
Author-email: emanuel@menttes.com, shuens@menttes.com
License: GPL2
Keywords: grok zope project management
Platform: UNKNOWN
Classifier: Development Status :: 4 - Beta
Classifier: Environment :: Web Environment
Classifier: Framework :: Zope3
Classifier: Intended Audience :: Other Audience
Classifier: License :: OSI Approved :: GNU General Public License (GPL)
Classifier: Operating System :: OS Independent
Classifier: Programming Language :: Python
Classifier: Topic :: Other/Nonlisted Topic
